HISTORY.rst
LICENSE
MANIFEST.in
README.rst
setup.py
chronos/__init__.py
chronos/main.py
chronos.egg-info/PKG-INFO
chronos.egg-info/SOURCES.txt
chronos.egg-info/dependency_links.txt
chronos.egg-info/entry_points.txt
chronos.egg-info/top_level.txt
test/__init__.py
test/test_trigger.py